orchat/__init__.py
orchat/main.py
orchat-1.4.3.dist-info/licenses/LICENSE
orchat-1.4.3.dist-info/METADATA
orchat-1.4.3.dist-info/WHEEL
orchat-1.4.3.dist-info/entry_points.txt
orchat-1.4.3.dist-info/top_level.txt
orchat-1.4.3.dist-info/RECORD
