Metadata-Version: 2.4
Name: orchat
Version: 1.4.3
Summary: A powerful CLI for chatting with AI models through OpenRouter
Home-page: https://github.com/oop7/OrChat
Author: oop7
Author-email: oop7 <oop7_support@proton.me>
License: MIT
Project-URL: Homepage, https://github.com/oop7/OrChat
Project-URL: Repository, https://github.com/oop7/OrChat
Project-URL: Bug Tracker, https://github.com/oop7/OrChat/issues
Project-URL: Reddit, https://www.reddit.com/r/NO-N_A_M_E/
Keywords: ai,chat,cli,openrouter,chatbot
Classifier: Programming Language :: Python :: 3
Classifier: License :: OSI Approved :: MIT License
Classifier: Operating System :: OS Independent
Requires-Python: >=3.9
License-File: LICENSE
Requires-Dist: requests
Requires-Dist: tiktoken
Requires-Dist: rich
Requires-Dist: python-dotenv
Requires-Dist: colorama
Requires-Dist: packaging
Requires-Dist: pyfzf
Requires-Dist: cryptography
Requires-Dist: prompt_toolkit
Dynamic: author
Dynamic: home-page
Dynamic: license-file
Dynamic: requires-python
